{
    "Configuration": {"Type":"Dispatching", "Version":1001, "Port":4511, "W":825, "H":290},
	"Title": {"FullName":"КЛ 220 кВ ТЭЦ-20-Пресня 1, 2", "MinName":"ПС Пресня ЧР", "SysName":"Система мониторинга частичных разрядов ПС Пресня"},
	"Info": {"ID":"DISP786CHRPRESN", "Subst":"786", "Type":"Dispatching", "Location":"ПС786/Сервер ТМ ПС Золотаревская", "NameMin":"ПС786 Дисп", "NameMax":"Модуль Дисп. ПС 786 ПС Золотаревская"},
	"LOG":
	[
		{"ID_Program" : "AUTO100"},
		{"ID_Program" : "DISP786CHRPRESN"},
		{"ID_Program" : "GS786/CHRPRESN"}
	],
	"Coord":"PS786",
	"LINKS":
	[
		 {"TypeLink" : "Autorization", "IP" : "0.0.0.0", "Port" : "4000"},
		 {"TypeLink" : "Back", "IP" : "0.0.0.0", "Port" : "4503"},
		 {"TypeLink" : "Home", "IP" : "0.0.0.0", "Port" : "4004"}
	],
	"Subscribe":[
    
        {"Topic":"IEC60870-5-104 to MQTT Gateway/Золотаревская(786)/СМЧР(ТЭЦ-12 - Пресня 1, 2 ПС Пресня)",
        "ASDU":1, "TOPIC_ID":6,  "IpList":["10.22.32.21:2757"]}

    ],
	"TELE":
	[
		{"L_TOPIC_ID":6, "SysId":"CHRPRESN", "DATA": [
		
		{ "ID":"726", "VER":"General", "TypeTele":"TM", "IOA":"700",  "Mes":"",   "NAME":"Общая активность ЧР (NQN) - положительная фаза ТЭЦ12 - Пресня №1 Муфта №1 Фаза Ж ВЧДТ1 БОД ЧР, Шкаф ЧР №137 ПС Пресня", "Links":{ "Arch":"4538"}},
		{ "ID":"727", "VER":"General", "TypeTele":"TM", "IOA":"800",  "Mes":"",   "NAME":"Общая активность ЧР (NQN) - отрицательная фаза ТЭЦ12 - Пресня №1 Муфта №1 Фаза Ж ВЧДТ1 БОД ЧР, Шкаф ЧР №137 ПС Пресня", "Links":{ "Arch":"4538"}},
		{ "ID":"728", "VER":"General", "TypeTele":"TM", "IOA":"400",  "Mes":"мВ",   "NAME":"Максимальная величина амплитуды импульсов ЧР (QM) - положительная фаза ТЭЦ12 - Пресня №1 Муфта №1 Фаза Ж ВЧДТ1  БОД ЧР, Шкаф ЧР №137 ПС Пресня", "Links":{ "Arch":"4538"}},
		{ "ID":"729", "VER":"General", "TypeTele":"TM", "IOA":"500",  "Mes":"мВ",   "NAME":"Максимальная величина амплитуды импульсов ЧР (QM) - отрицательная фаза ТЭЦ12 - Пресня №1 Муфта №1 Фаза Ж ВЧДТ1  БОД ЧР, Шкаф ЧР №137 ПС Пресня", "Links":{ "Arch":"4538"}},
		{ "ID":"730", "VER":"General", "TypeTele":"TM", "IOA":"701",  "Mes":"",   "NAME":"Общая активность ЧР (NQN) - положительная фаза ТЭЦ12 - Пресня №1 Муфта №2 Фаза З ВЧДТ2 БОД ЧР, Шкаф ЧР №137 ПС Пресня", "Links":{ "Arch":"4538"}},
		{ "ID":"731", "VER":"General", "TypeTele":"TM", "IOA":"801",  "Mes":"",   "NAME":"Общая активность ЧР (NQN) - отрицательная фаза ТЭЦ12 - Пресня №1 Муфта №2 Фаза З ВЧДТ2 БОД ЧР, Шкаф ЧР №137 ПС Пресня", "Links":{ "Arch":"4538"}},
		{ "ID":"732", "VER":"General", "TypeTele":"TM", "IOA":"401",  "Mes":"мВ",   "NAME":"Максимальная величина амплитуды импульсов ЧР (QM) - положительная фаза ТЭЦ12 - Пресня №1 Муфта №2 Фаза З ВЧДТ2  БОД ЧР, Шкаф ЧР №137 ПС Пресня", "Links":{ "Arch":"4538"}},
		{ "ID":"733", "VER":"General", "TypeTele":"TM", "IOA":"501",  "Mes":"мВ",   "NAME":"Максимальная величина амплитуды импульсов ЧР (QM) - отрицательная фаза ТЭЦ12 - Пресня №1 Муфта №2 Фаза З ВЧДТ2  БОД ЧР, Шкаф ЧР №137 ПС Пресня", "Links":{ "Arch":"4538"}},
		{ "ID":"734", "VER":"General", "TypeTele":"TM", "IOA":"702",  "Mes":"",   "NAME":"Общая активность ЧР (NQN) - положительная фаза ТЭЦ12 - Пресня №1 Муфта №3 Фаза К ВЧДТ3 БОД ЧР, Шкаф ЧР №137 ПС Пресня", "Links":{ "Arch":"4538"}},
		{ "ID":"735", "VER":"General", "TypeTele":"TM", "IOA":"802",  "Mes":"",   "NAME":"Общая активность ЧР (NQN) - отрицательная фаза ТЭЦ12 - Пресня №1 Муфта №3 Фаза К ВЧДТ3 БОД ЧР, Шкаф ЧР №137 ПС Пресня", "Links":{ "Arch":"4538"}},
		{ "ID":"736", "VER":"General", "TypeTele":"TM", "IOA":"402",  "Mes":"мВ",   "NAME":"Максимальная величина амплитуды импульсов ЧР (QM) - положительная фаза ТЭЦ12 - Пресня №1 Муфта №3 Фаза К ВЧДТ3  БОД ЧР, Шкаф ЧР №137 ПС Пресня", "Links":{ "Arch":"4538"}},
		{ "ID":"737", "VER":"General", "TypeTele":"TM", "IOA":"502",  "Mes":"мВ",   "NAME":"Максимальная величина амплитуды импульсов ЧР (QM) - отрицательная фаза ТЭЦ12 - Пресня №1 Муфта №3 Фаза К ВЧДТ3  БОД ЧР, Шкаф ЧР №137 ПС Пресня", "Links":{ "Arch":"4538"}},
		{ "ID":"738", "VER":"General", "TypeTele":"TM", "IOA":"706",  "Mes":"",   "NAME":"Общая активность ЧР (NQN) - положительная фаза ТЭЦ12 - Пресня №1 Муфта №1 Фаза Ж АкД1 БОД ЧР, Шкаф ЧР №137 ПС Пресня", "Links":{ "Arch":"4538"}},
		{ "ID":"739", "VER":"General", "TypeTele":"TM", "IOA":"806",  "Mes":"",   "NAME":"Общая активность ЧР (NQN) - отрицательная фаза ТЭЦ12 - Пресня №1 Муфта №1 Фаза Ж АкД1 БОД ЧР, Шкаф ЧР №137 ПС Пресня", "Links":{ "Arch":"4538"}},
		{ "ID":"740", "VER":"General", "TypeTele":"TM", "IOA":"406",  "Mes":"мВ",   "NAME":"Максимальная величина амплитуды импульсов ЧР (QM) - положительная фаза ТЭЦ12 - Пресня №1 Муфта №1 Фаза Ж АкД1  БОД ЧР, Шкаф ЧР №137 ПС Пресня", "Links":{ "Arch":"4538"}},
		{ "ID":"741", "VER":"General", "TypeTele":"TM", "IOA":"506",  "Mes":"мВ",   "NAME":"Максимальная величина амплитуды импульсов ЧР (QM) - отрицательная фаза ТЭЦ12 - Пресня №1 Муфта №1 Фаза Ж АкД1  БОД ЧР, Шкаф ЧР №137 ПС Пресня", "Links":{ "Arch":"4538"}},
		{ "ID":"742", "VER":"General", "TypeTele":"TM", "IOA":"707",  "Mes":"",   "NAME":"Общая активность ЧР (NQN) - положительная фаза ТЭЦ12 - Пресня №1 Муфта №2 Фаза З АкД2 БОД ЧР, Шкаф ЧР №137 ПС Пресня", "Links":{ "Arch":"4538"}},
		{ "ID":"743", "VER":"General", "TypeTele":"TM", "IOA":"807",  "Mes":"",   "NAME":"Общая активность ЧР (NQN) - отрицательная фаза ТЭЦ12 - Пресня №1 Муфта №2 Фаза З АкД2 БОД ЧР, Шкаф ЧР №137 ПС Пресня", "Links":{ "Arch":"4538"}},
		{ "ID":"744", "VER":"General", "TypeTele":"TM", "IOA":"407",  "Mes":"мВ",   "NAME":"Максимальная величина амплитуды импульсов ЧР (QM) - положительная фаза ТЭЦ12 - Пресня №1 Муфта №2 Фаза З АкД2  БОД ЧР, Шкаф ЧР №137 ПС Пресня", "Links":{ "Arch":"4538"}},
		{ "ID":"745", "VER":"General", "TypeTele":"TM", "IOA":"507",  "Mes":"мВ",   "NAME":"Максимальная величина амплитуды импульсов ЧР (QM) - отрицательная фаза ТЭЦ12 - Пресня №1 Муфта №2 Фаза З АкД2  БОД ЧР, Шкаф ЧР №137 ПС Пресня", "Links":{ "Arch":"4538"}},
		{ "ID":"746", "VER":"General", "TypeTele":"TM", "IOA":"708",  "Mes":"",   "NAME":"Общая активность ЧР (NQN) - положительная фаза ТЭЦ12 - Пресня №1 Муфта №3 Фаза К АкД3 БОД ЧР, Шкаф ЧР №137 ПС Пресня", "Links":{ "Arch":"4538"}},
		{ "ID":"747", "VER":"General", "TypeTele":"TM", "IOA":"808",  "Mes":"",   "NAME":"Общая активность ЧР (NQN) - отрицательная фаза ТЭЦ12 - Пресня №1 Муфта №3 Фаза К АкД3 БОД ЧР, Шкаф ЧР №137 ПС Пресня", "Links":{ "Arch":"4538"}},
		{ "ID":"748", "VER":"General", "TypeTele":"TM", "IOA":"408",  "Mes":"мВ",   "NAME":"Максимальная величина амплитуды импульсов ЧР (QM) - положительная фаза ТЭЦ12 - Пресня №1 Муфта №3 Фаза К АкД3  БОД ЧР, Шкаф ЧР №137 ПС Пресня", "Links":{ "Arch":"4538"}},
		{ "ID":"749", "VER":"General", "TypeTele":"TM", "IOA":"508",  "Mes":"мВ",   "NAME":"Максимальная величина амплитуды импульсов ЧР (QM) - отрицательная фаза ТЭЦ12 - Пресня №1 Муфта №3 Фаза К АкД3  БОД ЧР, Шкаф ЧР №137 ПС Пресня", "Links":{ "Arch":"4538"}},
		{ "ID":"750", "VER":"General", "TypeTele":"TM", "IOA":"703",  "Mes":"",   "NAME":"Общая активность ЧР (NQN) - положительная фаза ТЭЦ12 - Пресня №2 Муфта №4 Фаза Ж ВЧДТ4 БОД ЧР, Шкаф ЧР №137 ПС Пресня", "Links":{ "Arch":"4538"}},
		{ "ID":"751", "VER":"General", "TypeTele":"TM", "IOA":"803",  "Mes":"",   "NAME":"Общая активность ЧР (NQN) - отрицательная фаза ТЭЦ12 - Пресня №2 Муфта №4 Фаза Ж ВЧДТ4 БОД ЧР, Шкаф ЧР №137 ПС Пресня", "Links":{ "Arch":"4538"}},
		{ "ID":"752", "VER":"General", "TypeTele":"TM", "IOA":"403",  "Mes":"мВ",   "NAME":"Максимальная величина амплитуды импульсов ЧР (QM) - положительная фаза ТЭЦ12 - Пресня №2 Муфта №4 Фаза Ж ВЧДТ4  БОД ЧР, Шкаф ЧР №137 ПС Пресня", "Links":{ "Arch":"4538"}},
		{ "ID":"753", "VER":"General", "TypeTele":"TM", "IOA":"503",  "Mes":"мВ",   "NAME":"Максимальная величина амплитуды импульсов ЧР (QM) - отрицательная фаза ТЭЦ12 - Пресня №2 Муфта №4 Фаза Ж ВЧДТ4  БОД ЧР, Шкаф ЧР №137 ПС Пресня", "Links":{ "Arch":"4538"}},
		{ "ID":"754", "VER":"General", "TypeTele":"TM", "IOA":"704",  "Mes":"",   "NAME":"Общая активность ЧР (NQN) - положительная фаза ТЭЦ12 - Пресня №2 Муфта №5 Фаза З ВЧДТ5 БОД ЧР, Шкаф ЧР №137 ПС Пресня", "Links":{ "Arch":"4538"}},
		{ "ID":"755", "VER":"General", "TypeTele":"TM", "IOA":"804",  "Mes":"",   "NAME":"Общая активность ЧР (NQN) - отрицательная фаза ТЭЦ12 - Пресня №2 Муфта №5 Фаза З ВЧДТ5 БОД ЧР, Шкаф ЧР №137 ПС Пресня", "Links":{ "Arch":"4538"}},
		{ "ID":"756", "VER":"General", "TypeTele":"TM", "IOA":"404",  "Mes":"мВ",   "NAME":"Максимальная величина амплитуды импульсов ЧР (QM) - положительная фаза ТЭЦ12 - Пресня №2 Муфта №5 Фаза З ВЧДТ5  БОД ЧР, Шкаф ЧР №137 ПС Пресня", "Links":{ "Arch":"4538"}},
		{ "ID":"757", "VER":"General", "TypeTele":"TM", "IOA":"504",  "Mes":"мВ",   "NAME":"Максимальная величина амплитуды импульсов ЧР (QM) - отрицательная фаза ТЭЦ12 - Пресня №2 Муфта №5 Фаза З ВЧДТ5  БОД ЧР, Шкаф ЧР №137 ПС Пресня", "Links":{ "Arch":"4538"}},
		{ "ID":"758", "VER":"General", "TypeTele":"TM", "IOA":"705",  "Mes":"",   "NAME":"Общая активность ЧР (NQN) - положительная фаза ТЭЦ12 - Пресня №2 Муфта №6 Фаза К ВЧДТ6 БОД ЧР, Шкаф ЧР №137 ПС Пресня", "Links":{ "Arch":"4538"}},
		{ "ID":"759", "VER":"General", "TypeTele":"TM", "IOA":"805",  "Mes":"",   "NAME":"Общая активность ЧР (NQN) - отрицательная фаза ТЭЦ12 - Пресня №2 Муфта №6 Фаза К ВЧДТ6 БОД ЧР, Шкаф ЧР №137 ПС Пресня", "Links":{ "Arch":"4538"}},
		{ "ID":"760", "VER":"General", "TypeTele":"TM", "IOA":"405",  "Mes":"мВ",   "NAME":"Максимальная величина амплитуды импульсов ЧР (QM) - положительная фаза ТЭЦ12 - Пресня №2 Муфта №6 Фаза К ВЧДТ6  БОД ЧР, Шкаф ЧР №137 ПС Пресня", "Links":{ "Arch":"4538"}},
		{ "ID":"761", "VER":"General", "TypeTele":"TM", "IOA":"505",  "Mes":"мВ",   "NAME":"Максимальная величина амплитуды импульсов ЧР (QM) - отрицательная фаза ТЭЦ12 - Пресня №2 Муфта №6 Фаза К ВЧДТ6  БОД ЧР, Шкаф ЧР №137 ПС Пресня", "Links":{ "Arch":"4538"}},
		{ "ID":"762", "VER":"General", "TypeTele":"TM", "IOA":"710",  "Mes":"",   "NAME":"Общая активность ЧР (NQN) - положительная фаза ТЭЦ12 - Пресня №2 Муфта №4 Фаза Ж АкД4 БОД ЧР, Шкаф ЧР №137 ПС Пресня", "Links":{ "Arch":"4538"}},
		{ "ID":"763", "VER":"General", "TypeTele":"TM", "IOA":"810",  "Mes":"",   "NAME":"Общая активность ЧР (NQN) - отрицательная фаза ТЭЦ12 - Пресня №2 Муфта №4 Фаза Ж АкД4 БОД ЧР, Шкаф ЧР №137 ПС Пресня", "Links":{ "Arch":"4538"}},
		{ "ID":"764", "VER":"General", "TypeTele":"TM", "IOA":"410",  "Mes":"мВ",   "NAME":"Максимальная величина амплитуды импульсов ЧР (QM) - положительная фаза ТЭЦ12 - Пресня №2 Муфта №4 Фаза Ж АкД4  БОД ЧР, Шкаф ЧР №137 ПС Пресня", "Links":{ "Arch":"4538"}},
		{ "ID":"765", "VER":"General", "TypeTele":"TM", "IOA":"510",  "Mes":"мВ",   "NAME":"Максимальная величина амплитуды импульсов ЧР (QM) - отрицательная фаза ТЭЦ12 - Пресня №2 Муфта №4 Фаза Ж АкД4  БОД ЧР, Шкаф ЧР №137 ПС Пресня", "Links":{ "Arch":"4538"}},
		{ "ID":"766", "VER":"General", "TypeTele":"TM", "IOA":"711",  "Mes":"",   "NAME":"Общая активность ЧР (NQN) - положительная фаза ТЭЦ12 - Пресня №2 Муфта №5 Фаза З АкД5 БОД ЧР, Шкаф ЧР №137 ПС Пресня", "Links":{ "Arch":"4538"}},
		{ "ID":"767", "VER":"General", "TypeTele":"TM", "IOA":"811",  "Mes":"",   "NAME":"Общая активность ЧР (NQN) - отрицательная фаза ТЭЦ12 - Пресня №2 Муфта №5 Фаза З АкД5 БОД ЧР, Шкаф ЧР №137 ПС Пресня", "Links":{ "Arch":"4538"}},
		{ "ID":"768", "VER":"General", "TypeTele":"TM", "IOA":"411",  "Mes":"мВ",   "NAME":"Максимальная величина амплитуды импульсов ЧР (QM) - положительная фаза ТЭЦ12 - Пресня №2 Муфта №5 Фаза З АкД5  БОД ЧР, Шкаф ЧР №137 ПС Пресня", "Links":{ "Arch":"4538"}},
		{ "ID":"769", "VER":"General", "TypeTele":"TM", "IOA":"511",  "Mes":"мВ",   "NAME":"Максимальная величина амплитуды импульсов ЧР (QM) - отрицательная фаза ТЭЦ12 - Пресня №2 Муфта №5 Фаза З АкД5  БОД ЧР, Шкаф ЧР №137 ПС Пресня", "Links":{ "Arch":"4538"}},
		{ "ID":"770", "VER":"General", "TypeTele":"TM", "IOA":"712",  "Mes":"",   "NAME":"Общая активность ЧР (NQN) - положительная фаза ТЭЦ12 - Пресня №2 Муфта №6 Фаза К АкД6 БОД ЧР, Шкаф ЧР №137 ПС Пресня", "Links":{ "Arch":"4538"}},
		{ "ID":"771", "VER":"General", "TypeTele":"TM", "IOA":"812",  "Mes":"",   "NAME":"Общая активность ЧР (NQN) - отрицательная фаза ТЭЦ12 - Пресня №2 Муфта №6 Фаза К АкД6 БОД ЧР, Шкаф ЧР №137 ПС Пресня", "Links":{ "Arch":"4538"}},
		{ "ID":"772", "VER":"General", "TypeTele":"TM", "IOA":"412",  "Mes":"мВ",   "NAME":"Максимальная величина амплитуды импульсов ЧР (QM) - положительная фаза ТЭЦ12 - Пресня №2 Муфта №6 Фаза К АкД6  БОД ЧР, Шкаф ЧР №137 ПС Пресня", "Links":{ "Arch":"4538"}},
		{ "ID":"773", "VER":"General", "TypeTele":"TM", "IOA":"412",  "Mes":"мВ",   "NAME":"Максимальная величина амплитуды импульсов ЧР (QM) - отрицательная фаза ТЭЦ12 - Пресня №2 Муфта №6 Фаза К АкД6  БОД ЧР, Шкаф ЧР №137 ПС Пресня", "Links":{ "Arch":"4538"}},
		{ "ID":"774", "VER":"General", "TypeTele":"TS", "IOA":"100",  "Mes":"", "TypeAlarm":"Alarm",    "NAME":"Тревога - аварийное состояние ЧР ТЭЦ12 - Пресня №1 Муфта №1 Фаза Ж ВЧДТ1 БОД ЧР, Шкаф ЧР №137 ПС Пресня", "Links":{ "Arch":"4538"}},
		{ "ID":"775", "VER":"General", "TypeTele":"TS", "IOA":"101",  "Mes":"", "TypeAlarm":"Warning",  "NAME":"Предупреждение - предаварийное состояние ЧР ТЭЦ12 - Пресня №1 Муфта №1 Фаза Ж ВЧДТ1 БОД ЧР, Шкаф ЧР №137 ПС Пресня", "Links":{ "Arch":"4538"}},
		{ "ID":"776", "VER":"General", "TypeTele":"TS", "IOA":"104",  "Mes":"", "TypeAlarm":"Alarm",    "NAME":"Тревога - аварийное состояние ЧР ТЭЦ12 - Пресня №1 Муфта №2 Фаза З ВЧДТ2 БОД ЧР, Шкаф ЧР №137 ПС Пресня", "Links":{ "Arch":"4538"}},
		{ "ID":"777", "VER":"General", "TypeTele":"TS", "IOA":"105",  "Mes":"", "TypeAlarm":"Warning",  "NAME":"Предупреждение - предаварийное состояние ЧР ТЭЦ12 - Пресня №1 Муфта №2 Фаза З ВЧДТ2 БОД ЧР, Шкаф ЧР №137 ПС Пресня", "Links":{ "Arch":"4538"}},
		{ "ID":"778", "VER":"General", "TypeTele":"TS", "IOA":"108",  "Mes":"", "TypeAlarm":"Alarm",    "NAME":"Тревога - аварийное состояние ЧР ТЭЦ12 - Пресня №1 Муфта №3 Фаза К ВЧДТ3 БОД ЧР, Шкаф ЧР №137 ПС Пресня", "Links":{ "Arch":"4538"}},
		{ "ID":"779", "VER":"General", "TypeTele":"TS", "IOA":"109",  "Mes":"", "TypeAlarm":"Warning",  "NAME":"Предупреждение - предаварийное состояние ЧР ТЭЦ12 - Пресня №1 Муфта №3 Фаза К ВЧДТ3 БОД ЧР, Шкаф ЧР №137 ПС Пресня", "Links":{ "Arch":"4538"}},
		{ "ID":"780", "VER":"General", "TypeTele":"TS", "IOA":"124",  "Mes":"", "TypeAlarm":"Alarm",    "NAME":"Тревога - аварийное состояние ЧР ТЭЦ12 - Пресня №1 Муфта №1 Фаза Ж АкД1 БОД ЧР, Шкаф ЧР №137 ПС Пресня", "Links":{ "Arch":"4538"}},
		{ "ID":"781", "VER":"General", "TypeTele":"TS", "IOA":"125",  "Mes":"", "TypeAlarm":"Warning",  "NAME":"Предупреждение - предаварийное состояние ЧР ТЭЦ12 - Пресня №1 Муфта №1 Фаза Ж АкД1 БОД ЧР, Шкаф ЧР №137 ПС Пресня", "Links":{ "Arch":"4538"}},
		{ "ID":"782", "VER":"General", "TypeTele":"TS", "IOA":"128",  "Mes":"", "TypeAlarm":"Alarm",    "NAME":"Тревога - аварийное состояние ЧР ТЭЦ12 - Пресня №1 Муфта №2 Фаза З АкД2 БОД ЧР, Шкаф ЧР №137 ПС Пресня", "Links":{ "Arch":"4538"}},
		{ "ID":"783", "VER":"General", "TypeTele":"TS", "IOA":"129",  "Mes":"", "TypeAlarm":"Warning",  "NAME":"Предупреждение - предаварийное состояние ЧР ТЭЦ12 - Пресня №1 Муфта №2 Фаза З АкД2 БОД ЧР, Шкаф ЧР №137 ПС Пресня", "Links":{ "Arch":"4538"}},
		{ "ID":"784", "VER":"General", "TypeTele":"TS", "IOA":"132",  "Mes":"", "TypeAlarm":"Alarm",    "NAME":"Тревога - аварийное состояние ЧР ТЭЦ12 - Пресня №1 Муфта №3 Фаза К АкД3 БОД ЧР, Шкаф ЧР №137 ПС Пресня", "Links":{ "Arch":"4538"}},
		{ "ID":"785", "VER":"General", "TypeTele":"TS", "IOA":"133",  "Mes":"", "TypeAlarm":"Warning",  "NAME":"Предупреждение - предаварийное состояние ЧР ТЭЦ12 - Пресня №1 Муфта №3 Фаза К АкД3 БОД ЧР, Шкаф ЧР №137 ПС Пресня", "Links":{ "Arch":"4538"}},
		{ "ID":"786", "VER":"General", "TypeTele":"TS", "IOA":"112",  "Mes":"", "TypeAlarm":"Alarm",    "NAME":"Тревога - аварийное состояние ЧР ТЭЦ12 - Пресня №1 Муфта №4 Фаза Ж ВЧДТ4 БОД ЧР, Шкаф ЧР №137 ПС Пресня", "Links":{ "Arch":"4538"}},
		{ "ID":"787", "VER":"General", "TypeTele":"TS", "IOA":"113",  "Mes":"", "TypeAlarm":"Warning",  "NAME":"Предупреждение - предаварийное состояние ЧР ТЭЦ12 - Пресня №1 Муфта №4 Фаза Ж ВЧДТ4 БОД ЧР, Шкаф ЧР №137 ПС Пресня", "Links":{ "Arch":"4538"}},
		{ "ID":"788", "VER":"General", "TypeTele":"TS", "IOA":"116",  "Mes":"", "TypeAlarm":"Alarm",    "NAME":"Тревога - аварийное состояние ЧР ТЭЦ12 - Пресня №1 Муфта №5 Фаза З ВЧДТ5 БОД ЧР, Шкаф ЧР №137 ПС Пресня", "Links":{ "Arch":"4538"}},
		{ "ID":"789", "VER":"General", "TypeTele":"TS", "IOA":"117",  "Mes":"", "TypeAlarm":"Warning",  "NAME":"Предупреждение - предаварийное состояние ЧР ТЭЦ12 - Пресня №1 Муфта №5 Фаза З ВЧДТ5 БОД ЧР, Шкаф ЧР №137 ПС Пресня", "Links":{ "Arch":"4538"}},
		{ "ID":"790", "VER":"General", "TypeTele":"TS", "IOA":"120",  "Mes":"", "TypeAlarm":"Alarm",    "NAME":"Тревога - аварийное состояние ЧР ТЭЦ12 - Пресня №1 Муфта №6 Фаза К ВЧДТ6 БОД ЧР, Шкаф ЧР №137 ПС Пресня", "Links":{ "Arch":"4538"}},
		{ "ID":"791", "VER":"General", "TypeTele":"TS", "IOA":"121",  "Mes":"", "TypeAlarm":"Warning",  "NAME":"Предупреждение - предаварийное состояние ЧР ТЭЦ12 - Пресня №1 Муфта №6 Фаза К ВЧДТ6 БОД ЧР, Шкаф ЧР №137 ПС Пресня", "Links":{ "Arch":"4538"}},
		{ "ID":"792", "VER":"General", "TypeTele":"TS", "IOA":"140",  "Mes":"", "TypeAlarm":"Alarm",    "NAME":"Тревога - аварийное состояние ЧР ТЭЦ12 - Пресня №1 Муфта №4 Фаза Ж АкД4 БОД ЧР, Шкаф ЧР №137 ПС Пресня", "Links":{ "Arch":"4538"}},
		{ "ID":"793", "VER":"General", "TypeTele":"TS", "IOA":"141",  "Mes":"", "TypeAlarm":"Warning",  "NAME":"Предупреждение - предаварийное состояние ЧР ТЭЦ12 - Пресня №1 Муфта №4 Фаза Ж АкД4 БОД ЧР, Шкаф ЧР №137 ПС Пресня", "Links":{ "Arch":"4538"}},
		{ "ID":"794", "VER":"General", "TypeTele":"TS", "IOA":"144",  "Mes":"", "TypeAlarm":"Alarm",    "NAME":"Тревога - аварийное состояние ЧР ТЭЦ12 - Пресня №1 Муфта №5 Фаза З АкД5 БОД ЧР, Шкаф ЧР №137 ПС Пресня", "Links":{ "Arch":"4538"}},
		{ "ID":"795", "VER":"General", "TypeTele":"TS", "IOA":"145",  "Mes":"", "TypeAlarm":"Warning",  "NAME":"Предупреждение - предаварийное состояние ЧР ТЭЦ12 - Пресня №1 Муфта №5 Фаза З АкД5 БОД ЧР, Шкаф ЧР №137 ПС Пресня", "Links":{ "Arch":"4538"}},
		{ "ID":"796", "VER":"General", "TypeTele":"TS", "IOA":"148",  "Mes":"", "TypeAlarm":"Alarm",    "NAME":"Тревога - аварийное состояние ЧР ТЭЦ12 - Пресня №1 Муфта №6 Фаза К АкД6 БОД ЧР, Шкаф ЧР №137 ПС Пресня", "Links":{ "Arch":"4538"}},
		{ "ID":"797", "VER":"General", "TypeTele":"TS", "IOA":"149",  "Mes":"", "TypeAlarm":"Warning",  "NAME":"Предупреждение - предаварийное состояние ЧР ТЭЦ12 - Пресня №1 Муфта №6 Фаза К АкД6 БОД ЧР, Шкаф ЧР №137 ПС Пресня", "Links":{ "Arch":"4538"}}

		]}
    ],
	"ReqDataFromDB":{"Port":8081, "ReqData":[
		{"ID":"78611",	"NAME":"СМЧР конц. каб. муфт ТЭЦ20-Пресня 1,2 КРУЭ ТЭЦ20}"}
		]}
}
