{
    "Configuration": {"Type":"Dispatching", "Version":4809, "Port":4809, "W":825, "H":290},
	"Title": {"FullName":"КЛ 220 кВ Гражданская – Ваганьковская 1,2", "MinName":"ПС Ваганьковская ЧР 52", "SysName":"Система мониторинга частичных разрядов"},
	"Info": {"ID":"DISP848PD52", "Subst":"848", "Type":"Dispatching", "Location":"ПС848/Шкаф№52/ЧР", "NameMin":"ПС848 ТП Дисп", "NameMax":"Модуль Дисп. ПС Ваганьковская ЧР"},
	"LOG":
	[
		{"ID_Program" : "AUTO100"},
		{"ID_Program" : "DISP848PD52"},
		{"ID_Program" : "GS848/CHR52"}
	],
	"Coord":"PS848",
	"LINKS":
	[
		 {"TypeLink" : "Autorization", "IP" : "0.0.0.0", "Port" : "4000"},
		 {"TypeLink" : "Back", "IP" : "0.0.0.0", "Port" : "4803"},
		 {"TypeLink" : "Home", "IP" : "0.0.0.0", "Port" : "4004"}
	],



    "Subscribe":[
    
        {"Topic":"IEC60870-5-104 to MQTT Gateway/Ваганьковская(848)/СМЧР(пс Гражданская)",
        "ASDU":1, "TOPIC_ID":5,  "IpList":["10.22.36.23:2744"]},

		{"Topic":"IEC60870-5-104 to MQTT Gateway/Ваганьковская(848)/СМЧР(Гражданская - Ваганьковская 1, 2 пс Гражданская)",
        "ASDU":1, "TOPIC_ID":6,  "IpList":["10.22.36.23:2921"]}

    ],






    "TELE":
    [

{"L_TOPIC_ID":5, "SysId":"CHR52", "DATA": [
{"ID":"436", "TypeTele":"TM", "VER":"General", "IOA":"1113",  "Mes":"", "NAME":"Общая активность ЧР (NQN) - положительная фаза Гражданская - Ваганьковская №1 Муфта №1 Фаза Ж ВЧДТ1, ПС Гражданская", "Links":{ "Arch":"4838"}},
{"ID":"437", "TypeTele":"TM", "VER":"General", "IOA":"1114",  "Mes":"", "NAME":"Общая активность ЧР (NQN) - отрицательная фаза Гражданская - Ваганьковская №1 Муфта №1 Фаза Ж ВЧДТ1, ПС Гражданская", "Links":{ "Arch":"4838"}},
{"ID":"438", "TypeTele":"TM", "VER":"General", "IOA":"3045",  "Mes":"мВ", "NAME":"Максимальная величина амплитуды импульсов ЧР (QM) - положительная фаза Гражданская - Ваганьковская №1 Муфта №1 Фаза Ж ВЧДТ1, ПС Гражданская", "Links":{ "Arch":"4838"}},
{"ID":"439", "TypeTele":"TM", "VER":"General", "IOA":"3046",  "Mes":"мВ", "NAME":"Максимальная величина амплитуды импульсов ЧР (QM) - отрицательная фаза Гражданская - Ваганьковская №1 Муфта №1 Фаза Ж ВЧДТ1, ПС Гражданская", "Links":{ "Arch":"4838"}},
{"ID":"440", "TypeTele":"TM", "VER":"General", "IOA":"1117",  "Mes":"", "NAME":"Общая активность ЧР (NQN) - положительная фаза Гражданская - Ваганьковская №1 Муфта №2 Фаза З ВЧДТ2, ПС Гражданская", "Links":{ "Arch":"4838"}},
{"ID":"441", "TypeTele":"TM", "VER":"General", "IOA":"1118",  "Mes":"", "NAME":"Общая активность ЧР (NQN) - отрицательная фаза Гражданская - Ваганьковская №1 Муфта №2 Фаза З ВЧДТ2, ПС Гражданская", "Links":{ "Arch":"4838"}},
{"ID":"442", "TypeTele":"TM", "VER":"General", "IOA":"3047",  "Mes":"мВ", "NAME":"Максимальная величина амплитуды импульсов ЧР (QM) - положительная фаза Гражданская - Ваганьковская №1 Муфта №2 Фаза З ВЧДТ2, ПС Гражданская", "Links":{ "Arch":"4838"}},
{"ID":"443", "TypeTele":"TM", "VER":"General", "IOA":"3048",  "Mes":"мВ", "NAME":"Максимальная величина амплитуды импульсов ЧР (QM) - отрицательная фаза Гражданская - Ваганьковская №1 Муфта №2 Фаза З ВЧДТ2, ПС Гражданская", "Links":{ "Arch":"4838"}},
{"ID":"444", "TypeTele":"TM", "VER":"General", "IOA":"1121",  "Mes":"", "NAME":"Общая активность ЧР (NQN) - положительная фаза Гражданская - Ваганьковская №1 Муфта №3 Фаза К ВЧДТ3, ПС Гражданская", "Links":{ "Arch":"4838"}},
{"ID":"445", "TypeTele":"TM", "VER":"General", "IOA":"1122",  "Mes":"", "NAME":"Общая активность ЧР (NQN) - отрицательная фаза Гражданская - Ваганьковская №1 Муфта №3 Фаза К ВЧДТ3, ПС Гражданская", "Links":{ "Arch":"4838"}},
{"ID":"446", "TypeTele":"TM", "VER":"General", "IOA":"3049",  "Mes":"мВ", "NAME":"Максимальная величина амплитуды импульсов ЧР (QM) - положительная фаза Гражданская - Ваганьковская №1 Муфта №3 Фаза К ВЧДТ3, ПС Гражданская", "Links":{ "Arch":"4838"}},
{"ID":"447", "TypeTele":"TM", "VER":"General", "IOA":"3050",  "Mes":"мВ", "NAME":"Максимальная величина амплитуды импульсов ЧР (QM) - отрицательная фаза Гражданская - Ваганьковская №1 Муфта №3 Фаза К ВЧДТ3, ПС Гражданская", "Links":{ "Arch":"4838"}},
{"ID":"448", "TypeTele":"TM", "VER":"General", "IOA":"1137",  "Mes":"", "NAME":"Общая активность ЧР (NQN) - положительная фаза Гражданская - Ваганьковская №1 Муфта №1 Фаза Ж АкД1, ПС Гражданская", "Links":{ "Arch":"4838"}},
{"ID":"449", "TypeTele":"TM", "VER":"General", "IOA":"1138",  "Mes":"", "NAME":"Общая активность ЧР (NQN) - отрицательная фаза Гражданская - Ваганьковская №1 Муфта №1 Фаза Ж АкД1, ПС Гражданская", "Links":{ "Arch":"4838"}},
{"ID":"450", "TypeTele":"TM", "VER":"General", "IOA":"3057",  "Mes":"мВ", "NAME":"Максимальная величина амплитуды импульсов ЧР (QM) - положительная фаза Гражданская - Ваганьковская №1 Муфта №1 Фаза Ж АкД1, ПС Гражданская", "Links":{ "Arch":"4838"}},
{"ID":"451", "TypeTele":"TM", "VER":"General", "IOA":"3058",  "Mes":"мВ", "NAME":"Максимальная величина амплитуды импульсов ЧР (QM) - отрицательная фаза Гражданская - Ваганьковская №1 Муфта №1 Фаза Ж АкД1, ПС Гражданская", "Links":{ "Arch":"4838"}},
{"ID":"452", "TypeTele":"TM", "VER":"General", "IOA":"1141",  "Mes":"", "NAME":"Общая активность ЧР (NQN) - положительная фаза Гражданская - Ваганьковская №1 Муфта №2 Фаза З АкД2, ПС Гражданская", "Links":{ "Arch":"4838"}},
{"ID":"453", "TypeTele":"TM", "VER":"General", "IOA":"1142",  "Mes":"", "NAME":"Общая активность ЧР (NQN) - отрицательная фаза Гражданская - Ваганьковская №1 Муфта №2 Фаза З АкД2, ПС Гражданская", "Links":{ "Arch":"4838"}},
{"ID":"454", "TypeTele":"TM", "VER":"General", "IOA":"3059",  "Mes":"мВ", "NAME":"Максимальная величина амплитуды импульсов ЧР (QM) - положительная фаза Гражданская - Ваганьковская №1 Муфта №2 Фаза З АкД2, ПС Гражданская", "Links":{ "Arch":"4838"}},
{"ID":"455", "TypeTele":"TM", "VER":"General", "IOA":"3060",  "Mes":"мВ", "NAME":"Максимальная величина амплитуды импульсов ЧР (QM) - отрицательная фаза Гражданская - Ваганьковская №1 Муфта №2 Фаза З АкД2, ПС Гражданская", "Links":{ "Arch":"4838"}},
{"ID":"456", "TypeTele":"TM", "VER":"General", "IOA":"1145",  "Mes":"", "NAME":"Общая активность ЧР (NQN) - положительная фаза Гражданская - Ваганьковская №1 Муфта №3 Фаза К АкД3, ПС Гражданская", "Links":{ "Arch":"4838"}},
{"ID":"457", "TypeTele":"TM", "VER":"General", "IOA":"1146",  "Mes":"", "NAME":"Общая активность ЧР (NQN) - отрицательная фаза Гражданская - Ваганьковская №1 Муфта №3 Фаза К АкД3, ПС Гражданская", "Links":{ "Arch":"4838"}},
{"ID":"458", "TypeTele":"TM", "VER":"General", "IOA":"3061",  "Mes":"мВ", "NAME":"Максимальная величина амплитуды импульсов ЧР (QM) - положительная фаза Гражданская - Ваганьковская №1 Муфта №3 Фаза К АкД3, ПС Гражданская", "Links":{ "Arch":"4838"}},
{"ID":"459", "TypeTele":"TM", "VER":"General", "IOA":"3062",  "Mes":"мВ", "NAME":"Максимальная величина амплитуды импульсов ЧР (QM) - отрицательная фаза Гражданская - Ваганьковская №1 Муфта №3 Фаза К АкД3, ПС Гражданская", "Links":{ "Arch":"4838"}},
{"ID":"460", "TypeTele":"TM", "VER":"General", "IOA":"1125",  "Mes":"", "NAME":"Общая активность ЧР (NQN) - положительная фаза Гражданская - Ваганьковская №2 Муфта №4 Фаза Ж ВЧДТ4, ПС Гражданская", "Links":{ "Arch":"4838"}},
{"ID":"461", "TypeTele":"TM", "VER":"General", "IOA":"1126",  "Mes":"", "NAME":"Общая активность ЧР (NQN) - отрицательная фаза Гражданская - Ваганьковская №2 Муфта №4 Фаза Ж ВЧДТ4, ПС Гражданская", "Links":{ "Arch":"4838"}},
{"ID":"462", "TypeTele":"TM", "VER":"General", "IOA":"3051",  "Mes":"мВ", "NAME":"Максимальная величина амплитуды импульсов ЧР (QM) - положительная фаза Гражданская - Ваганьковская №2 Муфта №4 Фаза Ж ВЧДТ4, ПС Гражданская", "Links":{ "Arch":"4838"}},
{"ID":"463", "TypeTele":"TM", "VER":"General", "IOA":"3052",  "Mes":"мВ", "NAME":"Максимальная величина амплитуды импульсов ЧР (QM) - отрицательная фаза Гражданская - Ваганьковская №2 Муфта №4 Фаза Ж ВЧДТ4, ПС Гражданская", "Links":{ "Arch":"4838"}},
{"ID":"464", "TypeTele":"TM", "VER":"General", "IOA":"1129",  "Mes":"", "NAME":"Общая активность ЧР (NQN) - положительная фаза Гражданская - Ваганьковская №2 Муфта №5 Фаза З ВЧДТ5, ПС Гражданская", "Links":{ "Arch":"4838"}},
{"ID":"465", "TypeTele":"TM", "VER":"General", "IOA":"1130",  "Mes":"", "NAME":"Общая активность ЧР (NQN) - отрицательная фаза Гражданская - Ваганьковская №2 Муфта №5 Фаза З ВЧДТ5, ПС Гражданская", "Links":{ "Arch":"4838"}},
{"ID":"466", "TypeTele":"TM", "VER":"General", "IOA":"3053",  "Mes":"мВ", "NAME":"Максимальная величина амплитуды импульсов ЧР (QM) - положительная фаза Гражданская - Ваганьковская №2 Муфта №5 Фаза З ВЧДТ5, ПС Гражданская", "Links":{ "Arch":"4838"}},
{"ID":"467", "TypeTele":"TM", "VER":"General", "IOA":"3054",  "Mes":"мВ", "NAME":"Максимальная величина амплитуды импульсов ЧР (QM) - отрицательная фаза Гражданская - Ваганьковская №2 Муфта №5 Фаза З ВЧДТ5, ПС Гражданская", "Links":{ "Arch":"4838"}},
{"ID":"468", "TypeTele":"TM", "VER":"General", "IOA":"1133",  "Mes":"", "NAME":"Общая активность ЧР (NQN) - положительная фаза Гражданская - Ваганьковская №2 Муфта №6 Фаза К ВЧДТ6, ПС Гражданская", "Links":{ "Arch":"4838"}},
{"ID":"469", "TypeTele":"TM", "VER":"General", "IOA":"1134",  "Mes":"", "NAME":"Общая активность ЧР (NQN) - отрицательная фаза Гражданская - Ваганьковская №2 Муфта №6 Фаза К ВЧДТ6, ПС Гражданская", "Links":{ "Arch":"4838"}},
{"ID":"470", "TypeTele":"TM", "VER":"General", "IOA":"3055",  "Mes":"мВ", "NAME":"Максимальная величина амплитуды импульсов ЧР (QM) - положительная фаза Гражданская - Ваганьковская №2 Муфта №6 Фаза К ВЧДТ6, ПС Гражданская", "Links":{ "Arch":"4838"}},
{"ID":"471", "TypeTele":"TM", "VER":"General", "IOA":"3056",  "Mes":"мВ", "NAME":"Максимальная величина амплитуды импульсов ЧР (QM) - отрицательная фаза Гражданская - Ваганьковская №2 Муфта №6 Фаза К ВЧДТ6, ПС Гражданская", "Links":{ "Arch":"4838"}},
{"ID":"472", "TypeTele":"TM", "VER":"General", "IOA":"1173",  "Mes":"", "NAME":"Общая активность ЧР (NQN) - положительная фаза Гражданская - Ваганьковская №2 Муфта №4 Фаза Ж АкД4, ПС Гражданская", "Links":{ "Arch":"4838"}},
{"ID":"473", "TypeTele":"TM", "VER":"General", "IOA":"1174",  "Mes":"", "NAME":"Общая активность ЧР (NQN) - отрицательная фаза Гражданская - Ваганьковская №2 Муфта №4 Фаза Ж АкД4, ПС Гражданская", "Links":{ "Arch":"4838"}},
{"ID":"474", "TypeTele":"TM", "VER":"General", "IOA":"3075",  "Mes":"мВ", "NAME":"Максимальная величина амплитуды импульсов ЧР (QM) - положительная фаза Гражданская - Ваганьковская №2 Муфта №4 Фаза Ж АкД4, ПС Гражданская", "Links":{ "Arch":"4838"}},
{"ID":"475", "TypeTele":"TM", "VER":"General", "IOA":"3076",  "Mes":"мВ", "NAME":"Максимальная величина амплитуды импульсов ЧР (QM) - отрицательная фаза Гражданская - Ваганьковская №2 Муфта №4 Фаза Ж АкД4, ПС Гражданская", "Links":{ "Arch":"4838"}},
{"ID":"476", "TypeTele":"TM", "VER":"General", "IOA":"1177",  "Mes":"", "NAME":"Общая активность ЧР (NQN) - положительная фаза Гражданская - Ваганьковская №2 Муфта №5 Фаза З АкД5, ПС Гражданская", "Links":{ "Arch":"4838"}},
{"ID":"477", "TypeTele":"TM", "VER":"General", "IOA":"1178",  "Mes":"", "NAME":"Общая активность ЧР (NQN) - отрицательная фаза Гражданская - Ваганьковская №2 Муфта №5 Фаза З АкД5, ПС Гражданская", "Links":{ "Arch":"4838"}},
{"ID":"478", "TypeTele":"TM", "VER":"General", "IOA":"3077",  "Mes":"мВ", "NAME":"Максимальная величина амплитуды импульсов ЧР (QM) - положительная фаза Гражданская - Ваганьковская №2 Муфта №5 Фаза З АкД5, ПС Гражданская", "Links":{ "Arch":"4838"}},
{"ID":"479", "TypeTele":"TM", "VER":"General", "IOA":"3078",  "Mes":"мВ", "NAME":"Максимальная величина амплитуды импульсов ЧР (QM) - отрицательная фаза Гражданская - Ваганьковская №2 Муфта №5 Фаза З АкД5, ПС Гражданская", "Links":{ "Arch":"4838"}},
{"ID":"480", "TypeTele":"TM", "VER":"General", "IOA":"1181",  "Mes":"", "NAME":"Общая активность ЧР (NQN) - положительная фаза Гражданская - Ваганьковская №2 Муфта №6 Фаза К АкД6, ПС Гражданская", "Links":{ "Arch":"4838"}},
{"ID":"481", "TypeTele":"TM", "VER":"General", "IOA":"1182",  "Mes":"", "NAME":"Общая активность ЧР (NQN) - отрицательная фаза Гражданская - Ваганьковская №2 Муфта №6 Фаза К АкД6, ПС Гражданская", "Links":{ "Arch":"4838"}},
{"ID":"482", "TypeTele":"TM", "VER":"General", "IOA":"3079",  "Mes":"мВ", "NAME":"Максимальная величина амплитуды импульсов ЧР (QM) - положительная фаза Гражданская - Ваганьковская №2 Муфта №6 Фаза К АкД6, ПС Гражданская", "Links":{ "Arch":"4838"}},
{"ID":"483", "TypeTele":"TM", "VER":"General", "IOA":"3080",  "Mes":"мВ", "NAME":"Максимальная величина амплитуды импульсов ЧР (QM) - отрицательная фаза Гражданская - Ваганьковская №2 Муфта №6 Фаза К АкД6, ПС Гражданская", "Links":{ "Arch":"4838"}},

{"ID":"486", "TypeTele":"TS", "TypeAlarm":"Alarm", "VER":"General", "IOA":"1116",  "Mes":"", "NAME":"Тревога - аварийное состояние ЧР Гражданская - Ваганьковская №1 Муфта №1 Фаза Ж ВЧДТ1, ПС Гражданская", "Links":{ "Arch":"4838"}},
{"ID":"487", "TypeTele":"TS", "TypeAlarm":"Warning", "VER":"General", "IOA":"1115",  "Mes":"", "NAME":"Предупреждение - предаварийное состояние ЧР Гражданская - Ваганьковская №1 Муфта №1 Фаза Ж ВЧДТ1, ПС Гражданская", "Links":{ "Arch":"4838"}},
{"ID":"488", "TypeTele":"TS", "TypeAlarm":"Alarm", "VER":"General", "IOA":"1120",  "Mes":"", "NAME":"Тревога - аварийное состояние ЧР Гражданская - Ваганьковская №1 Муфта №2 Фаза З ВЧДТ2, ПС Гражданская", "Links":{ "Arch":"4838"}},
{"ID":"489", "TypeTele":"TS", "TypeAlarm":"Warning", "VER":"General", "IOA":"1119",  "Mes":"", "NAME":"Предупреждение - предаварийное состояние ЧР Гражданская - Ваганьковская №1 Муфта №2 Фаза З ВЧДТ2, ПС Гражданская", "Links":{ "Arch":"4838"}},
{"ID":"490", "TypeTele":"TS", "TypeAlarm":"Alarm", "VER":"General", "IOA":"1124",  "Mes":"", "NAME":"Тревога - аварийное состояние ЧР Гражданская - Ваганьковская №1 Муфта №3 Фаза К ВЧДТ3, ПС Гражданская", "Links":{ "Arch":"4838"}},
{"ID":"491", "TypeTele":"TS", "TypeAlarm":"Warning", "VER":"General", "IOA":"1123",  "Mes":"", "NAME":"Предупреждение - предаварийное состояние ЧР Гражданская - Ваганьковская №1 Муфта №3 Фаза К ВЧДТ3, ПС Гражданская", "Links":{ "Arch":"4838"}},
{"ID":"492", "TypeTele":"TS", "TypeAlarm":"Alarm", "VER":"General", "IOA":"1140",  "Mes":"", "NAME":"Тревога - аварийное состояние ЧР Гражданская - Ваганьковская №1 Муфта №1 Фаза Ж АкД1, ПС Гражданская", "Links":{ "Arch":"4838"}},
{"ID":"493", "TypeTele":"TS", "TypeAlarm":"Warning", "VER":"General", "IOA":"1139",  "Mes":"", "NAME":"Предупреждение - предаварийное состояние ЧР Гражданская - Ваганьковская №1 Муфта №1 Фаза Ж АкД1, ПС Гражданская", "Links":{ "Arch":"4838"}},
{"ID":"494", "TypeTele":"TS", "TypeAlarm":"Alarm", "VER":"General", "IOA":"1144",  "Mes":"", "NAME":"Тревога - аварийное состояние ЧР Гражданская - Ваганьковская №1 Муфта №2 Фаза З АкД2, ПС Гражданская", "Links":{ "Arch":"4838"}},
{"ID":"495", "TypeTele":"TS", "TypeAlarm":"Warning", "VER":"General", "IOA":"1143",  "Mes":"", "NAME":"Предупреждение - предаварийное состояние ЧР Гражданская - Ваганьковская №1 Муфта №2 Фаза З АкД2, ПС Гражданская", "Links":{ "Arch":"4838"}},
{"ID":"496", "TypeTele":"TS", "TypeAlarm":"Alarm", "VER":"General", "IOA":"1148",  "Mes":"", "NAME":"Тревога - аварийное состояние ЧР Гражданская - Ваганьковская №1 Муфта №3 Фаза К АкД3, ПС Гражданская", "Links":{ "Arch":"4838"}},
{"ID":"497", "TypeTele":"TS", "TypeAlarm":"Warning", "VER":"General", "IOA":"1147",  "Mes":"", "NAME":"Предупреждение - предаварийное состояние ЧР Гражданская - Ваганьковская №1 Муфта №3 Фаза К АкД3, ПС Гражданская", "Links":{ "Arch":"4838"}},
{"ID":"498", "TypeTele":"TS", "TypeAlarm":"Alarm", "VER":"General", "IOA":"1128",  "Mes":"", "NAME":"Тревога - аварийное состояние ЧР Гражданская - Ваганьковская №2 Муфта №4 Фаза Ж ВЧДТ4, ПС Гражданская", "Links":{ "Arch":"4838"}},
{"ID":"499", "TypeTele":"TS", "TypeAlarm":"Warning", "VER":"General", "IOA":"1127",  "Mes":"", "NAME":"Предупреждение - предаварийное состояние ЧР Гражданская - Ваганьковская №2 Муфта №4 Фаза Ж ВЧДТ4, ПС Гражданская", "Links":{ "Arch":"4838"}},
{"ID":"500", "TypeTele":"TS", "TypeAlarm":"Alarm", "VER":"General", "IOA":"1132",  "Mes":"", "NAME":"Тревога - аварийное состояние ЧР Гражданская - Ваганьковская №2 Муфта №5 Фаза З ВЧДТ5, ПС Гражданская", "Links":{ "Arch":"4838"}},
{"ID":"501", "TypeTele":"TS", "TypeAlarm":"Warning", "VER":"General", "IOA":"1131",  "Mes":"", "NAME":"Предупреждение - предаварийное состояние ЧР Гражданская - Ваганьковская №2 Муфта №5 Фаза З ВЧДТ5, ПС Гражданская", "Links":{ "Arch":"4838"}},
{"ID":"502", "TypeTele":"TS", "TypeAlarm":"Alarm", "VER":"General", "IOA":"1136",  "Mes":"", "NAME":"Тревога - аварийное состояние ЧР Гражданская - Ваганьковская №2 Муфта №6 Фаза К ВЧДТ6, ПС Гражданская", "Links":{ "Arch":"4838"}},
{"ID":"503", "TypeTele":"TS", "TypeAlarm":"Warning", "VER":"General", "IOA":"1135",  "Mes":"", "NAME":"Предупреждение - предаварийное состояние ЧР Гражданская - Ваганьковская №2 Муфта №6 Фаза К ВЧДТ6, ПС Гражданская", "Links":{ "Arch":"4838"}},
{"ID":"504", "TypeTele":"TS", "TypeAlarm":"Alarm", "VER":"General", "IOA":"1176",  "Mes":"", "NAME":"Тревога - аварийное состояние ЧР Гражданская - Ваганьковская №2 Муфта №4 Фаза Ж АкД4, ПС Гражданская", "Links":{ "Arch":"4838"}},
{"ID":"505", "TypeTele":"TS", "TypeAlarm":"Warning", "VER":"General", "IOA":"1175",  "Mes":"", "NAME":"Предупреждение - предаварийное состояние ЧР Гражданская - Ваганьковская №2 Муфта №4 Фаза Ж АкД4, ПС Гражданская", "Links":{ "Arch":"4838"}},
{"ID":"506", "TypeTele":"TS", "TypeAlarm":"Alarm", "VER":"General", "IOA":"1180",  "Mes":"", "NAME":"Тревога - аварийное состояние ЧР Гражданская - Ваганьковская №2 Муфта №5 Фаза З АкД5, ПС Гражданская", "Links":{ "Arch":"4838"}},
{"ID":"507", "TypeTele":"TS", "TypeAlarm":"Warning", "VER":"General", "IOA":"1179",  "Mes":"", "NAME":"Предупреждение - предаварийное состояние ЧР Гражданская - Ваганьковская №2 Муфта №5 Фаза З АкД5, ПС Гражданская", "Links":{ "Arch":"4838"}},
{"ID":"508", "TypeTele":"TS", "TypeAlarm":"Alarm", "VER":"General", "IOA":"1184",  "Mes":"", "NAME":"Тревога - аварийное состояние ЧР Гражданская - Ваганьковская №2 Муфта №6 Фаза К АкД6, ПС Гражданская", "Links":{ "Arch":"4838"}},
{"ID":"509", "TypeTele":"TS", "TypeAlarm":"Warning", "VER":"General", "IOA":"1183",  "Mes":"", "NAME":"Предупреждение - предаварийное состояние ЧР Гражданская - Ваганьковская №2 Муфта №6 Фаза К АкД6, ПС Гражданская", "Links":{ "Arch":"4838"}}

	]},
{"L_TOPIC_ID":6, "SysId":"CHR52", "DATA": [
{"ID":"484", "TypeTele":"TM", "VER":"General", "IOA":"2004",  "Mes":"В", "NAME":"Напряжение на батареях ИБП, Стойка №52, ПС Гражданская", "Links":{ "Arch":"4838"}},
{"ID":"485", "TypeTele":"TM", "VER":"General", "IOA":"2002",  "Mes":"%", "NAME":"Степень заряда батарей ИБП, Стойка №52, ПС Гражданская", "Links":{ "Arch":"4838"}},
{"ID":"511", "TypeTele":"TS", "TypeAlarm":"Alarm", "VER":"General", "IOA":"2000",  "Mes":"", "NAME":"Отсутствие напряжения питания на стойке (работа от батареи), Стойка №52, ПС Гражданская", "Links":{ "Arch":"4838"}},
{"ID":"512", "TypeTele":"TS", "TypeAlarm":"Alarm", "VER":"General", "IOA":"2001",  "Mes":"", "NAME":"Неисправность батарей ИБП, Стойка №52, ПС Гражданская", "Links":{ "Arch":"4838"}},
{"ID":"513", "TypeTele":"TS", "TypeAlarm":"Alarm", "VER":"General", "IOA":"2003",  "Mes":"", "NAME":"Низкий заряд батарей ИБП, Стойка №52, ПС Гражданская", "Links":{ "Arch":"4838"}}
	]}		

],
	"ReqDataFromDB":{"Port":8081, "ReqData":[
		{"ID":"8489",	"NAME":"СМЧР конц. каб. муфт Гражданская-Ваганьковская 1,2; ПС Гражданская}"}
		]}
}

